rasterx/__init__.py
rasterx-0.0.0.dist-info/METADATA
rasterx-0.0.0.dist-info/WHEEL
rasterx-0.0.0.dist-info/top_level.txt
rasterx-0.0.0.dist-info/RECORD
